{
    "$schema": "https://schema.management.azure.com/schemas/2018-05-01/subscriptionDeploymentTemplate.json#",
    "contentVersion": "1.0.0.1",
    "parameters": {
        "resourceGroupNamePrefix": {
            "type": "string"
        },
        "resourceGrouplocation": {
            "type": "string"
        },
        "instanceCount": {
            "type": "int"
        }
    },
    "variables": {},
    "resources": [
        {
            "type": "Microsoft.Resources/resourceGroups",
            "apiVersion": "2018-05-01",
            "location": "[parameters('resourceGroupLocation')]",
            "name": "[concat(parameters('resourceGroupNamePrefix'), copyIndex())]",
            "copy": {
                "name": "rgCopy",
                "count": "[parameters('instanceCount')]"
            },
            "properties": {}
        }
    ],
    "outputs": {}
}